odoo8_addon_website_snippet_country_dropdown-8.0.1.1.0.99.dev6-py2.7-nspkg.pth
odoo8_addon_website_snippet_country_dropdown-8.0.1.1.0.99.dev6.dist-info/DESCRIPTION.rst
odoo8_addon_website_snippet_country_dropdown-8.0.1.1.0.99.dev6.dist-info/METADATA
odoo8_addon_website_snippet_country_dropdown-8.0.1.1.0.99.dev6.dist-info/RECORD
odoo8_addon_website_snippet_country_dropdown-8.0.1.1.0.99.dev6.dist-info/WHEEL
odoo8_addon_website_snippet_country_dropdown-8.0.1.1.0.99.dev6.dist-info/metadata.json
odoo8_addon_website_snippet_country_dropdown-8.0.1.1.0.99.dev6.dist-info/namespace_packages.txt
odoo8_addon_website_snippet_country_dropdown-8.0.1.1.0.99.dev6.dist-info/top_level.txt
odoo_addons/website_snippet_country_dropdown/README.rst
odoo_addons/website_snippet_country_dropdown/__init__.py
odoo_addons/website_snippet_country_dropdown/__openerp__.py
odoo_addons/website_snippet_country_dropdown/demo/pages.xml
odoo_addons/website_snippet_country_dropdown/i18n/es.po
odoo_addons/website_snippet_country_dropdown/i18n/fr.po
odoo_addons/website_snippet_country_dropdown/i18n/pt_BR.po
odoo_addons/website_snippet_country_dropdown/i18n/sl.po
odoo_addons/website_snippet_country_dropdown/i18n/website_snippet_country_dropdown.pot
odoo_addons/website_snippet_country_dropdown/static/description/icon.png
odoo_addons/website_snippet_country_dropdown/static/src/css/style.css
odoo_addons/website_snippet_country_dropdown/static/src/css/style.css.map
odoo_addons/website_snippet_country_dropdown/static/src/css/style.sass
odoo_addons/website_snippet_country_dropdown/static/src/img/dropdown.png
odoo_addons/website_snippet_country_dropdown/static/src/js/website_snippet_country_dropdown.editor.js
odoo_addons/website_snippet_country_dropdown/static/src/js/website_snippet_country_dropdown.js
odoo_addons/website_snippet_country_dropdown/static/src/xml/country_dropdown.xml
odoo_addons/website_snippet_country_dropdown/views/assets.xml
odoo_addons/website_snippet_country_dropdown/views/snippets.xml
